auto_chart_patterns/__init__.py
auto_chart_patterns/chart_pattern.py
auto_chart_patterns/flag_pennant_patterns.py
auto_chart_patterns/line.py
auto_chart_patterns/reversal_patterns.py
auto_chart_patterns/rsi_div_patterns.py
auto_chart_patterns/trendline_patterns.py
auto_chart_patterns/zigzag.py
auto_chart_patterns-0.2.12.dist-info/METADATA
auto_chart_patterns-0.2.12.dist-info/WHEEL
auto_chart_patterns-0.2.12.dist-info/licenses/LICENSE
auto_chart_patterns-0.2.12.dist-info/RECORD
