Metadata-Version: 2.4
Name: auto-chart-patterns
Version: 0.2.12
Summary: Automatically identify chart patterns from OHLC data
Project-URL: Homepage, https://github.com/FanM/auto-chart-patterns
Project-URL: Bug Tracker, https://github.com/FanM/auto-chart-patterns/issues
Author-email: Fan Mao <maofan@xsmail.com>
License-File: LICENSE
Classifier: License :: OSI Approved :: MIT License
Classifier: Operating System :: OS Independent
Classifier: Programming Language :: Python :: 3
Requires-Python: >=3.9
Requires-Dist: numpy>=1.19.0
Requires-Dist: pandas>=1.0.0
